{
    "invertiria": {
        "title": "Invertiria",
        "paragraph": "Invertiria es una pagina web de inversiones inmobiliarias",
        "getStarted": "Empezar gratis",
        "learnMore": "Saber más"
    },
    "investment": {
        "title": "Inversion",
        "paragraph": "Formulario de inversion",
        "click_on_the_map": "Haz clic en el mapa para seleccionar la ubicación",
        "results": "Resultados",
        "here_are_the_results": "Aquí están los resultados de tu inversion:"
    }
}